qsoptex.so
python_qsoptex-0.5.dist-info/DESCRIPTION.rst
python_qsoptex-0.5.dist-info/METADATA
python_qsoptex-0.5.dist-info/metadata.json
python_qsoptex-0.5.dist-info/RECORD
python_qsoptex-0.5.dist-info/top_level.txt
python_qsoptex-0.5.dist-info/WHEEL
