Metadata-Version: 2.0
Name: python-qsoptex
Version: 0.5
Summary: Python bindings for QSopt_ex, an exact linear programming solver
Home-page: https://github.com/jonls/python-qsoptex
Author: Jon Lund Steffensen
Author-email: jonlst@gmail.com
License: GPLv3+
Platform: UNKNOWN
Classifier: Development Status :: 4 - Beta
Classifier: Intended Audience :: Developers
Classifier: License :: OSI Approved :: GNU General Public License v3 or later (GPLv3+)
Classifier: Programming Language :: Cython
Classifier: Programming Language :: Python :: 2.7
Classifier: Programming Language :: Python :: 3.4
Classifier: Topic :: Scientific/Engineering :: Mathematics
Requires-Dist: six
